google/cloud/channel/__init__.py
google/cloud/channel/gapic_version.py
google/cloud/channel/py.typed
google/cloud/channel_v1/__init__.py
google/cloud/channel_v1/gapic_metadata.json
google/cloud/channel_v1/gapic_version.py
google/cloud/channel_v1/py.typed
google/cloud/channel_v1/services/__init__.py
google/cloud/channel_v1/services/cloud_channel_reports_service/__init__.py
google/cloud/channel_v1/services/cloud_channel_reports_service/async_client.py
google/cloud/channel_v1/services/cloud_channel_reports_service/client.py
google/cloud/channel_v1/services/cloud_channel_reports_service/pagers.py
google/cloud/channel_v1/services/cloud_channel_reports_service/transports/__init__.py
google/cloud/channel_v1/services/cloud_channel_reports_service/transports/base.py
google/cloud/channel_v1/services/cloud_channel_reports_service/transports/grpc.py
google/cloud/channel_v1/services/cloud_channel_reports_service/transports/grpc_asyncio.py
google/cloud/channel_v1/services/cloud_channel_service/__init__.py
google/cloud/channel_v1/services/cloud_channel_service/async_client.py
google/cloud/channel_v1/services/cloud_channel_service/client.py
google/cloud/channel_v1/services/cloud_channel_service/pagers.py
google/cloud/channel_v1/services/cloud_channel_service/transports/__init__.py
google/cloud/channel_v1/services/cloud_channel_service/transports/base.py
google/cloud/channel_v1/services/cloud_channel_service/transports/grpc.py
google/cloud/channel_v1/services/cloud_channel_service/transports/grpc_asyncio.py
google/cloud/channel_v1/types/__init__.py
google/cloud/channel_v1/types/billing_accounts.py
google/cloud/channel_v1/types/channel_partner_links.py
google/cloud/channel_v1/types/common.py
google/cloud/channel_v1/types/customers.py
google/cloud/channel_v1/types/entitlement_changes.py
google/cloud/channel_v1/types/entitlements.py
google/cloud/channel_v1/types/offers.py
google/cloud/channel_v1/types/operations.py
google/cloud/channel_v1/types/products.py
google_cloud_channel-1.26.0.dist-info/licenses/LICENSE
google_cloud_channel-1.26.0.dist-info/METADATA
google_cloud_channel-1.26.0.dist-info/WHEEL
google_cloud_channel-1.26.0.dist-info/top_level.txt
google_cloud_channel-1.26.0.dist-info/RECORD
